LICENSE
MANIFEST.in
README.rst
setup.cfg
setup.py
source/tpRenamer/__init__.py
source/tpRenamer/core/__init__.py
source/tpRenamer/core/exceptions.py
source/tpRenamer/core/renamer.py
source/tpRenamer/resources/icons/color/camera.png
source/tpRenamer/resources/icons/color/edit.png
source/tpRenamer/resources/icons/color/file.png
source/tpRenamer/resources/icons/color/layer.png
source/tpRenamer/resources/icons/color/light.png
source/tpRenamer/resources/icons/color/material.png
source/tpRenamer/resources/icons/color/object.png
source/tpRenamer/resources/icons/color/rename.png
source/tpRenamer/widgets/__init__.py
source/tpRenamer/widgets/autorenamewidget.py
source/tpRenamer/widgets/categorywidget.py
source/tpRenamer/widgets/manualrenamewidget.py
source/tpRenamer/widgets/renamerwidget.py
source/tpRenamer/widgets/replacerwidget.py
source/tprenamer.egg-info/PKG-INFO
source/tprenamer.egg-info/SOURCES.txt
source/tprenamer.egg-info/dependency_links.txt
source/tprenamer.egg-info/not-zip-safe
source/tprenamer.egg-info/requires.txt
source/tprenamer.egg-info/top_level.txt