Metadata-Version: 2.1
Name: tprenamer
Version: 0.0.1
Summary: Renamer Tool to easily rename DCC objects in a visual way
Home-page: https://github.com/tpoveda/tpRenamer
Author: Tomas Poveda
Author-email: tpovedatd@gmail.com
License: MIT
Platform: UNKNOWN
Provides-Extra: test
Provides-Extra: dev
